ValiotWorker/Logging.py
ValiotWorker/Notifications.py
ValiotWorker/__init__.py
ValiotWorker/__main__.py
ValiotWorker/__version__.py
ValiotWorker/croniter.py
ValiotWorker/croniterHelpers.py
ValiotWorker/dateHelpers.py
ValiotWorker/mutations.py
ValiotWorker/queries.py
ValiotWorker/redis.py
ValiotWorker/subscriptions.py
ValiotWorker/uploaders.py
ValiotWorker/worker.py
ValiotWorker/healthCheckProbe/__init__.py
ValiotWorker/healthCheckProbe/__main__.py
ValiotWorker/healthCheckProbe/modules/__init__.py
ValiotWorker/healthCheckProbe/modules/http_server.py
ValiotWorker-6.0.1.dist-info/LICENCE
ValiotWorker-6.0.1.dist-info/METADATA
ValiotWorker-6.0.1.dist-info/WHEEL
ValiotWorker-6.0.1.dist-info/entry_points.txt
ValiotWorker-6.0.1.dist-info/top_level.txt
ValiotWorker-6.0.1.dist-info/RECORD
