Metadata-Version: 2.1
Name: ValiotWorker
Version: 6.0.1
Summary: Enables running Python functions as standalone jobs based on interaction with valiot-jobs API
Home-page: https://github.com/valiot/python-gql-worker
Author: Valiot
Author-email: hiring@valiot.io
Keywords: ValiotWorker
License-File: LICENCE
Requires-Dist: colorama (<0.5,>=0.4)
Requires-Dist: croniter (<2.0,>=1.3)
Requires-Dist: pydash (<7.0,>=5.0)
Requires-Dist: pygqlc (<4.0,>=3.0)
Requires-Dist: python-dateutil (<3.0,>=2.8)
Requires-Dist: pytz (<2022.8,>=2022.2)
Requires-Dist: redis (<5.0,>=4.3)
Requires-Dist: singleton-decorator (<2.0,>=1.0)
Requires-Dist: termcolor (<3.0,>=2.0.1)
Requires-Dist: velebit-useful-logs (<2.0,>=1.0)
